xlseries/__init__.py
xlseries/run_all_tests.py
xlseries/xlseries.py
xlseries/strategies/__init__.py
xlseries/strategies/strategies.py
xlseries/strategies/clean/__init__.py
xlseries/strategies/clean/parse_time.py
xlseries/strategies/clean/time_index.py
xlseries/strategies/discover/__init__.py
xlseries/strategies/discover/parameters.py
xlseries/strategies/get/__init__.py
xlseries/strategies/get/data.py
xlseries/strategies/get/period_range.py
xlseries/tests/__init__.py
xlseries/tests/profiling.py
xlseries/tests/test_xlseries.py
xlseries/tests/yappi.callgrind
xlseries/tests/integration_cases/CASES.md
xlseries/tests/integration_cases/INPUT_PARAMETERS.md
xlseries/tests/integration_cases/Tests.xlsx
xlseries/tests/integration_cases/record.txt
xlseries/tests/integration_cases/expected/test_case1.csv
xlseries/tests/integration_cases/expected/test_case1.json
xlseries/tests/integration_cases/expected/test_case1.xlsx
xlseries/tests/integration_cases/expected/test_case2.xlsx
xlseries/tests/integration_cases/expected/test_case3.csv
xlseries/tests/integration_cases/expected/test_case3.json
xlseries/tests/integration_cases/expected/test_case3.xlsx
xlseries/tests/integration_cases/expected/test_case4.xlsx
xlseries/tests/integration_cases/expected/test_case5.xlsx
xlseries/tests/integration_cases/expected/test_case5_without_end.xlsx
xlseries/tests/integration_cases/expected/test_case6.xlsx
xlseries/tests/integration_cases/expected/test_case6_composed_headers.xlsx
xlseries/tests/integration_cases/expected/test_case6_context.xlsx
xlseries/tests/integration_cases/expected/test_case7.xlsx
xlseries/tests/integration_cases/expected/test_case2/test_case2a.csv
xlseries/tests/integration_cases/expected/test_case2/test_case2a.json
xlseries/tests/integration_cases/expected/test_case2/test_case2b.csv
xlseries/tests/integration_cases/expected/test_case2/test_case2b.json
xlseries/tests/integration_cases/original/test_case1.csv
xlseries/tests/integration_cases/original/test_case1.xlsx
xlseries-0.2.6.dist-info/AUTHORS.rst
xlseries-0.2.6.dist-info/LICENSE
xlseries-0.2.6.dist-info/METADATA
xlseries-0.2.6.dist-info/WHEEL
xlseries-0.2.6.dist-info/top_level.txt
xlseries-0.2.6.dist-info/RECORD
