Metadata-Version: 2.1
Name: xlseries
Version: 0.2.6
Summary: Python package to scrape time series data from excel files.
Home-page: https://github.com/abenassi/xlseries
Download-URL: https://github.com/abenassi/xlseries/archive/0.2.6.tar.gz
Author: Agustin Benassi
Author-email: agusbenassi@gmail.com
Maintainer: Agustin Benassi
Maintainer-email: agusbenassi@gmail.com
License: GPLv3+
Keywords: xlseries excel time series data opendata scraper
Classifier: Development Status :: 3 - Alpha
Classifier: Intended Audience :: Developers
Classifier: License :: OSI Approved :: GNU General Public License v3 or later (GPLv3+)
Classifier: Natural Language :: English
Classifier: Programming Language :: Python :: 3
Classifier: Programming Language :: Python :: 3.6
Classifier: Topic :: Office/Business
License-File: LICENSE
License-File: AUTHORS.rst
Requires-Dist: arrow (==0.5.4)
Requires-Dist: asn1crypto (==0.24.0)
Requires-Dist: certifi (==2019.6.16)
Requires-Dist: cffi (==1.12.3)
Requires-Dist: coverage (==4.5.4)
Requires-Dist: cryptography (==2.7)
Requires-Dist: et-xmlfile (==1.0.1)
Requires-Dist: jdcal (==1.4.1)
Requires-Dist: mock (==3.0.5)
Requires-Dist: nose (==1.3.7)
Requires-Dist: openpyxl (==2.5.0)
Requires-Dist: pandas (<=0.22,>=0.20)
Requires-Dist: Parsley (==1.3)
Requires-Dist: pycallgraph (==1.0.1)
Requires-Dist: pycparser (==2.19)
Requires-Dist: python-dateutil (==2.8.0)
Requires-Dist: pytz (==2019.2)
Requires-Dist: PyYAML (==5.1.2)
Requires-Dist: six (==1.12.0)
Requires-Dist: Unidecode (==0.4.21)
Requires-Dist: xlrd (==1.0.0)
